odoo/addons/account_invoice_tier_validation_forward/README.rst
odoo/addons/account_invoice_tier_validation_forward/__init__.py
odoo/addons/account_invoice_tier_validation_forward/__manifest__.py
odoo/addons/account_invoice_tier_validation_forward/i18n/account_invoice_tier_validation_forward.pot
odoo/addons/account_invoice_tier_validation_forward/readme/CONFIGURE.rst
odoo/addons/account_invoice_tier_validation_forward/readme/CONTRIBUTORS.rst
odoo/addons/account_invoice_tier_validation_forward/readme/DESCRIPTION.rst
odoo/addons/account_invoice_tier_validation_forward/readme/INSTALL.rst
odoo/addons/account_invoice_tier_validation_forward/static/description/icon.png
odoo/addons/account_invoice_tier_validation_forward/static/description/index.html
odoo/addons/account_invoice_tier_validation_forward/views/account_invoice_view.xml
odoo12_addon_account_invoice_tier_validation_forward-12.0.1.0.1.dist-info/METADATA
odoo12_addon_account_invoice_tier_validation_forward-12.0.1.0.1.dist-info/WHEEL
odoo12_addon_account_invoice_tier_validation_forward-12.0.1.0.1.dist-info/top_level.txt
odoo12_addon_account_invoice_tier_validation_forward-12.0.1.0.1.dist-info/RECORD
